README.rst
setup.py
fedex/__init__.py
fedex/address_validation_service.py
fedex/api.py
fedex/exceptions.py
fedex/rate_services.py
fedex/ship_services.py
fedex/structures.py
fedex/wsdl/AddressValidationService_v2.wsdl
fedex/wsdl/RateService_v13.wsdl
fedex/wsdl/ShipService_v15.wsdl
fedex/wsdl/ShipService_v9.wsdl
pyfedex.egg-info/PKG-INFO
pyfedex.egg-info/SOURCES.txt
pyfedex.egg-info/dependency_links.txt
pyfedex.egg-info/not-zip-safe
pyfedex.egg-info/requires.txt
pyfedex.egg-info/top_level.txt